{
 "date": "Sat, 30 Nov 2013 05:43:09 +0000",
 "message": "This is a beta release of LCOGT JSON. The format may change so any applications you build using this may need updating in the future.",
 "observation": {
  "about": "http://lcogt.net/observations/ogg/2m0a/18797",
  "avm": {
   "code": "3.6.3",
   "name": "Multiple Stars"
  },
  "credit": {
   "about": "http://creativecommons.org/licenses/by-nc/2.0/deed.en_US",
   "label": "Image taken with Las Cumbres Observatory Global Telescope Network, 1-meter telescope at McDonald Observatory"
  },
  "dec": 58.083100000000002,
  "exposure": 3.0,
  "filter": {
   "about": "http://lcogt.net/",
   "name": "Unknown"
  },
  "image": {
   "about": "http://lcogt.net/files/messier/M40.jpg",
   "fits": "",
   "label": "Image",
   "thumb": "http://lcogt.net/files/messier/M40_thumbnail.jpg"
  },
  "instr": {
   "about": "http://lcogt.net/site/mcdonald",
   "tel": "McDonald 1-meter"
  },
  "label": "M40 (Winnecke 4)",
  "observer": {
   "about": "http://lcogt.net/observations/user/1721",
   "label": "Jake Hughes, Cardiff University"
  },
  "ra": 185.5215,
  "time": {
   "creation": "Mon, 02 June 2014 11:29:51 +0000"
  },
  "views": 165
 }
}
